{
"tb_board_news": [
	{
		"news_id" : "중앙일보-사회-2022.08.17.11:34",
		"title" : "[속보] 검찰, '피살 공무원 월북 번복' 해경청 압수수색",
		"post" : "검찰이 '서해 공무원 피살 사건'과 관련해 해양경찰청에 대한 압수수색에 나섰다. 17일 법조계 등에 따르면 서울중앙지검은 이날 오전 인천시 연수구 송도국제도시에 있는 해경청 청사에 수사관 등을 보내 압수수색을 진행하고 있다. 검찰은 이날 해경청에서 확보한 당시 수사자료 등을 분석해 문재인 정부 청와대의 수사 개입 여부 등을 확인할 것으로 전해졌다.",
		"source" : "중앙일보",
		"category" : "사회",
		"news_date" : "2022.08.17 11:34",
		"link" : "https:\/\/www.joongang.co.kr\/article\/25094903",
		"img_url" : "https:\/\/pds.joongang.co.kr\/news\/component\/htmlphoto_mmdata\/202208\/17\/d7796044-9c5a-46ea-ae86-3012880b5aea.jpg\/_ir_205x115_\/",
		"reg_date" : "2022-08-17T02:50:01.590Z"
	}
	,
	{
		"news_id" : "중앙일보-사회-2022.08.17.12:16",
		"title" : "이 가격 실화냐? 12년째 짜장면 2000원 받는 '착한 중식집'",
		"post" : "인건비와 원부자재 가격 인상에도 짜장면을 2000원에 파는 ‘착한 가격업소’가 있어 화제다. 17일 연합뉴스에 따르면 인천 강화군 양도면에는 ‘짜장면 2000원, 탕수육 8000원’이라는 부담 없는 가격으로 중화요리를 제공하는 음식점이 있다. 인천에서 착한 가격업소에 포함된 중식집 중 김씨의 가게는 단연 가장 낮은 짜장면 값을 자랑한다.",
		"source" : "중앙일보",
		"category" : "사회",
		"news_date" : "2022.08.17 12:16",
		"link" : "https:\/\/www.joongang.co.kr\/article\/25094913",
		"img_url" : "https:\/\/pds.joongang.co.kr\/news\/component\/htmlphoto_mmdata\/202208\/17\/8a46e9bf-4ac6-4657-91a1-cfea28769ed0.jpg\/_ir_205x115_\/",
		"reg_date" : "2022-08-17T05:21:01.577Z"
	},
	{
		"news_id" : "중앙일보-사회-2022.08.17.14:50",
		"title" : "신규 확진 18만명, 넉달만 최다…재유행 정점 전망 근접",
		"post" : "이날 박향 중앙사고수습본부 방역총괄반장은 중앙재난안전대책본부(중대본) 브리핑에서 \"병상 운영 상황을 모니터링해본 결과 주말에 신속한 입원치료가 필요한 경우가 상당수 있었다\"며 \"고위험 산모, 신생아, 중증 기저질환자에 대한 보호 필요성이 높은 상황이라 수도권에 주말 당직병원을 운영하고자 한다\"고 말했다. 주말 당직병원이 수도권에서만 운영되는 것에 대한 우려가 나오자 박 반장은 \"최근 확진자의 50% 이상이 수도권에서 나오고 있기 때문\"이라며 \"비수도권의 경우 권역별로 병상 대응을 하고 있다. 일상을 제약당하면서 확진자 숫자를 줄이느냐, 아니면 조금 자유롭게 살면서 확진자 숫자를 어느 정도 용인하느냐를 결정해야 한다\"라며 \"거리두기를 할 만큼 확진자 숫자가 폭발하는 게 아니라면 고위험군에 대한 보호와 치료를 하면서 일상을 유지해나갈 수 있다\"고 말했다.",
		"source" : "중앙일보",
		"category" : "사회",
		"news_date" : "2022.08.17 14:50",
		"link" : "https:\/\/www.joongang.co.kr\/article\/25094937",
		"img_url" : "https:\/\/pds.joongang.co.kr\/news\/component\/htmlphoto_mmdata\/202208\/17\/d9d48209-aa09-40aa-9398-97ed913eb89f.jpg\/_ir_205x115_\/",
		"reg_date" : "2022-08-17T05:53:21.209Z"
	},
	{
		"news_id" : "중앙일보-사회-2022.08.17.14:24",
		"title" : "'제주 변호사 피살' 공모자 무죄 뒤집혔다…2심서 징역 12년",
		"post" : "제주의 대표적인 장기 미제 사건 중 하나인 ‘변호사 피살사건’에서 살인 범행을 공모한 혐의로 재판에 넘겨진 피고인이 살해 혐의에 대해 무죄를 선고받은 1심과 달리 항소심에서 징역 12년을 선고받았다. 광주고법 형사1부(부장 이경훈)는 17일 오전 항소심 선고공판에서 살인과 협박 혐의로 재판에 넘겨진 김모(56)씨에 대해 살해 혐의를 무죄로 판단한 원심판결을 파기하고 징역 12년을 선고했다. 재판부는 \"피고인은 재판 과정에서 피해자에게 상해를 가하는 범행을 지시하거나 음해했다는 사실을 인정했다\"며 \"무엇보다 피고인은 범행 당시 피해자를 사망에 이르게 할 수 있는 특별 제작된 흉기가 사용된 사실도 알고 있었다.",
		"source" : "중앙일보",
		"category" : "사회",
		"news_date" : "2022.08.17 14:24",
		"link" : "https:\/\/www.joongang.co.kr\/article\/25094932",
		"img_url" : "https:\/\/pds.joongang.co.kr\/news\/component\/htmlphoto_mmdata\/202208\/17\/8c878726-58da-4fb0-b08f-e9a107be1e28.jpg\/_ir_205x115_\/",
		"reg_date" : "2022-08-17T05:33:30.896Z"
	},
	{
		"news_id" : "중앙일보-사회-2022.08.17.13:49",
		"title" : "\"머리카락 사기, 식당에 5천만원 줬다\"던 유튜버 글 알고보니",
		"post" : "한 식당에서 음식에 머리카락이 나온 것처럼 꾸며 음식값을 환불받았다는 의혹이 제기된 유명 유튜버가, 자신이 식당에 5000만원을 배상했다는 일각의 주장에 대해 ‘사실무근’이라고 밝혔다. 같은 날 A씨는 자신의 유튜브 커뮤니티를 통해 해당 게시글을 언급하며 \"저를 사칭해 작성한 글이 돌아다닌다는 점을 확인했다. 앞서 지난 14일 KBS는 A씨 일행이 강원도 춘천에 있는 햄버거 가게에 방문해 음식에서 머리카락이 나온 것처럼 꾸며 음식값을 전액 환불받았다고 보도했다.",
		"source" : "중앙일보",
		"category" : "사회",
		"news_date" : "2022.08.17 13:49",
		"link" : "https:\/\/www.joongang.co.kr\/article\/25094925",
		"img_url" : "https:\/\/pds.joongang.co.kr\/news\/component\/htmlphoto_mmdata\/202208\/17\/08933a7e-862f-4be3-800a-8f32f0401cf7.jpg\/_ir_205x115_\/",
		"reg_date" : "2022-08-17T05:21:01.554Z"
	},
	{
		"news_id" : "중앙일보-사회-2022.08.17.13:19",
		"title" : "반도체 등 첨단분야 학과, 교원만 있으면 학생수 늘릴 수 있게 돼",
		"post" : "기존에는 땅·건물·교원·재산 등 4가지 조건을 모두 갖춰야 학생 수를 늘릴 수 있었지만 앞으로는 교원만 갖추면 된다. 17일 교육부는 반도체 등 첨단 분야 인재 양성을 위해 전문대학 또는 일반대학이 학부 정원을 늘릴 때 땅·건물·교원·재산 등 4대 조건을 모두 충족하도록 한 규제를 교원확보율(겸임·초빙교수 포함)만 충족하면 신설 또는 증설할 수 있도록 완화하겠다고 밝혔다. 교육부 관계자는 \"교원 1인당 학생 수가 계열별로 인문사회는 25명, 자연 계열은 20명으로 돼 있기 때문에 인문 계열 정원을 줄이고 자연 계열 정원을 늘리면 학교가 교원을 더 뽑아야 한다\"며 \"채용 부담 때문에 대학들이 자체 조정에 소극적이라는 의견이 있어서 이런 부담을 줄여주자는 취지\"라고 설명했다.",
		"source" : "중앙일보",
		"category" : "사회",
		"news_date" : "2022.08.17 13:19",
		"link" : "https:\/\/www.joongang.co.kr\/article\/25094922",
		"img_url" : "https:\/\/pds.joongang.co.kr\/news\/component\/htmlphoto_mmdata\/202208\/17\/008a2e68-10fb-4dda-af1c-7ee8d3cec095.jpg\/_ir_205x115_\/",
		"reg_date" : "2022-08-17T05:21:01.571Z"
	},
	{
		"news_id" : "중앙일보-사회-2022.08.17.13:12",
		"title" : "포천 광릉숲 국립수목원 상징물 ‘장수하늘소’…멸종위기 벗어나나",
		"post" : "경기도 포천 광릉숲 국립수목원의 상징물 중 하나인 장수하늘소를 멸종 위기에서 벗어나게 할 기틀이 마련됐다. 동시에 2017년, 2019년, 2020년에 발견됐던 개체들로부터 산란 받아 실내 사육하고 있는 개체를 더해 총 20개체를 방사했다, 1차로 지난 1일 암컷 7개체, 수컷 3개체를 방사한 데 이어 지난 16일 암컷 5개체, 수컷 5개체를 추가로 방사했다. 우리나라에서는 2006년 8월 국립수목원 내 전시원 주변에서 암컷 1개체, 2014년 8월 수컷 1개체가 각각 발견된 이래 매년 광릉숲 국립수목원에서 개체가 확인되고 있다.",
		"source" : "중앙일보",
		"category" : "사회",
		"news_date" : "2022.08.17 13:12",
		"link" : "https:\/\/www.joongang.co.kr\/article\/25094921",
		"img_url" : "https:\/\/pds.joongang.co.kr\/news\/component\/htmlphoto_mmdata\/202208\/17\/595080a1-e39d-471b-aee0-2e115a4a896e.jpg\/_ir_205x115_\/",
		"reg_date" : "2022-08-17T05:21:01.572Z"
	},
	{
		"news_id" : "중앙일보-사회-2022.08.17.12:30",
		"title" : "\"26년 키운 시험관 아기, 父만 유전자 불일치\"...의사 충격 답변",
		"post" : "서울의 한 대학병원에서 시험관 시술(체외 인공수정)로 얻은 아들의 유전자가 아버지와 일치하지 않는 황당한 일이 벌어졌다. 1996년 대학병원에서 시험관 아기 시술을 받은 50대 여성 A씨는 17일 CBS 라디오 ‘김현정의 뉴스쇼’에 출연해 \"유전자 검사 결과 아빠하고는 일치하는 게 전혀 없는 거로 나왔고, 엄마만 일치한다고 했다\"며 \"믿고 싶지 않았다. A씨는 \"아이가 네다섯살쯤 간염 항체 검사를 했는데 소아과 선생님이 ‘아이 A형인 거 알고 계시죠?’라고 했다\"며 \"잘못된 거 같다고 했더니 아니라고, 부모님이 잘못 알고 계신 거 아니냐고 했다\"고 당시 상황을 설명했다.",
		"source" : "중앙일보",
		"category" : "사회",
		"news_date" : "2022.08.17 12:30",
		"link" : "https:\/\/www.joongang.co.kr\/article\/25094918",
		"img_url" : "https:\/\/pds.joongang.co.kr\/news\/component\/htmlphoto_mmdata\/202208\/17\/bc790fa7-c687-4a0e-8a81-062b9d7b8199.jpg\/_ir_205x115_\/",
		"reg_date" : "2022-08-17T05:21:01.573Z"
	},
	{
		"news_id" : "중앙일보-사회-2022.08.17.12:18",
		"title" : "스토킹 범죄자도 전자발찌 찬다…법무부 입법예고",
		"post" : "살인·성폭력 등 범죄에만 부착할 수 있는 위치추적 전자장치(전자발찌)가 앞으로는 스토킹 범죄까지 확대된다. 이에 법무부는 살인·성폭력·강도·미성년자 유괴범죄에만 전자발찌 부착을 명령할 수 있는 현행법을 스토킹범죄까지 확대하기로 했다. 한동훈 법무부장관은 \"스토킹범죄는 처벌받은 범죄자가 동일 또는 유사 피해자를 상대로 재범할 가능성이 높은 범죄여서 전자발찌 부착이 가장 필요했는데도 불가능했다\"며 \"이번 개정안으로 국가가 스토킹범죄 피해자를 실질적으로 보호하는 계기를 마련하겠다\"고 밝혔다.",
		"source" : "중앙일보",
		"category" : "사회",
		"news_date" : "2022.08.17 12:18",
		"link" : "https:\/\/www.joongang.co.kr\/article\/25094915",
		"img_url" : "https:\/\/pds.joongang.co.kr\/news\/component\/htmlphoto_mmdata\/202208\/17\/21d4e147-4030-49ed-90a3-f6ffb77637a4.jpg\/_ir_205x115_\/",
		"reg_date" : "2022-08-17T05:21:01.576Z"
	},
	{
		"news_id" : "중앙일보-사회-2022.08.17.11:48",
		"title" : "길거리 주운 지갑서 '수상한 봉투'…666명분 마약 있었다",
		"post" : "지갑을 잃어버리는 바람에 수백 명이 투약할 수 있는 양의 마약을 소지하고 있던 것이 드러난 중년 남성이 경찰에 붙잡혔다. 지갑 안 봉지에 들어있던 가루는 약 20ｇ으로, 간이시약 검사에서 필로폰 양성반응이 나와 국립과학수사연구원에서 정밀 검사를 진행 중이다. A씨와 B씨도 검거 후 이뤄진 간이시약 검사에서 필로폰 양성 반응이 나온 것으로 알려졌다.",
		"source" : "중앙일보",
		"category" : "사회",
		"news_date" : "2022.08.17 11:48",
		"link" : "https:\/\/www.joongang.co.kr\/article\/25094909",
		"img_url" : "https:\/\/pds.joongang.co.kr\/news\/component\/htmlphoto_mmdata\/202208\/17\/63059c81-12c2-466d-9e2e-985326d180a6.jpg\/_ir_205x115_\/",
		"reg_date" : "2022-08-17T02:50:01.560Z"
	},
	{
		"news_id" : "중앙일보-사회-2022.08.17.11:33",
		"title" : "택시 잡으려고 왕복 8차로 무단횡단한 30대…차에 치어 사망",
		"post" : "왕복 8차선 도로에서 무단횡단을 하던 30대 남성이 차에 치여 숨졌다. A씨는 전날 오후 10시 2분께 인천 남동구 구월동의 왕복 8차로에서 QM6 승용차를 몰고 가다 무단횡단을 하던 30대 남성 B씨를 치어 숨지게 한 혐의를 받고 있다. 조사 결과 A씨는 당시 음주 상태는 아니었으며, 택시를 잡기 위해 도로를 가로지르던 B씨를 미처 보지 못하고 사고를 낸 것으로 파악됐다.",
		"source" : "중앙일보",
		"category" : "사회",
		"news_date" : "2022.08.17 11:33",
		"link" : "https:\/\/www.joongang.co.kr\/article\/25094902",
		"img_url" : "https:\/\/pds.joongang.co.kr\/news\/component\/htmlphoto_mmdata\/202208\/17\/ea547b85-4121-4506-9b64-3870b97f717d.jpg\/_ir_205x115_\/",
		"reg_date" : "2022-08-17T02:50:01.602Z"
	},
	{
		"news_id" : "중앙일보-사회-2022.08.17.11:31",
		"title" : "'허리디스크 파열' 정경심 형집행정지 되나…이르면 18일 결정",
		"post" : "정 전 교수는 지난 1월 대법원에서 자녀 입시 비리 및 사모펀드 관련 자본시장법 위반 혐의 등이 유죄가 인정돼 징역 4년형을 확정받고 수감 중이다. 딸 조민씨의 허위스펙 조성 등 입시 비리와 사모펀드 관련 혐의(업무방해, 자본시장법 위반 등)로 지난 1월 징역 4년이 확정된 정 전 교수는 지난 1일 \"허리 디스크 파열·협착, 하지마비 등에 대한 신속한 수술이 필요하다\"는 이유로 서울중앙지검에 형집행정지 신청서를 냈다. 정 전 교수의 변호인에 따르면, 정 전 교수는 지난 6~7월 수감 중인 서울구치소에서 수차례 낙상 사고를 당했고, 이후 디스크 파열 진단을 받았다.",
		"source" : "중앙일보",
		"category" : "사회",
		"news_date" : "2022.08.17 11:31",
		"link" : "https:\/\/www.joongang.co.kr\/article\/25094901",
		"img_url" : "https:\/\/pds.joongang.co.kr\/news\/component\/htmlphoto_mmdata\/202208\/17\/a7037691-c286-41f5-b428-17b8d0442846.jpg\/_ir_205x115_\/",
		"reg_date" : "2022-08-17T02:50:01.614Z"
	},
	{
		"news_id" : "중앙일보-사회-2022.08.17.11:02",
		"title" : "조국 '정경심이 도피 지시' 보도 손배소…法 \"1000만원 배상\"",
		"post" : "17일 서울중앙지법 민사14부(서보민 부장판사)는 조 전 장관 측이 세계일보와 소속 기자 2명을 상대로 낸 정정보도 및 손해배상 소송에서 조 전 장관에게 500만원, 정경심 전 교수에게 500만원씩 모두 1000만원을 배상하라고 판결했다. 조 전 장관 측은 2019년 9월 5일자 세계일보 「[단독] \"펀드 관련자들 해외 도피 조국 아내 지시 따른 것\"」이란 제목의 기사에 대해 2020년 8월 정정보도와 1억원 손해배상을 청구하는 소송을 제기했다. 해당 기사는 조 전 장관의 인사청문회 직전 정 전 교수가 조 전 장관의 5촌 조카인 조범동씨와 사모펀드 운용사 관계자들에게 ‘해외로 나가 있으라’고 지시했다는 내용을 담고 있다.",
		"source" : "중앙일보",
		"category" : "사회",
		"news_date" : "2022.08.17 11:02",
		"link" : "https:\/\/www.joongang.co.kr\/article\/25094894",
		"img_url" : "https:\/\/pds.joongang.co.kr\/news\/component\/htmlphoto_mmdata\/202208\/17\/eed277cf-6433-43aa-8357-cdba52c25ddb.jpg\/_ir_205x115_\/",
		"reg_date" : "2022-08-17T02:19:01.453Z"
	},
	{
		"news_id" : "중앙일보-사회-2022.08.17.11:00",
		"title" : "\"울릉군→독도군 바꾸자\"…75세 독도 열정맨이 발견한 근거",
		"post" : "전 재산을 털어 독도 관련 지리 박물관을 지은 70대 퇴임 교사가 '경상북도 울릉군 울릉읍' 행정지명을 '경상북도 독도군 울릉읍'으로 바꾸자고 제안했다. 양 관장은 \"한국령 독도인 것을 밝히기 위해 보통은 『삼국사기』에 나오는 우산국(于山國)을 영토적 당위성을 찾는데, 우산국은 울릉도이고 독도는 울릉도의 부속 섬으로 간주하려 하는 것\"이라며 \"하지만 세종실록지리지를 보면 우산은 우산도(독도)이고, 다른 한 섬인 무릉은 무릉도(울릉도)로 나온다\"고 설명했다. 양 관장은 \"따라서 우산국을 울릉도라고 단정 짓기보다는 우산국의 명칭 자체를 우산도(독도) 속에 울릉도를 포함한 한국 영토 경계를 함축한 '독도의 역사적 기록'으로 봐야 할 것이다\"고 독도군 개칭 제안의 근거를 전했다.",
		"source" : "중앙일보",
		"category" : "사회",
		"news_date" : "2022.08.17 11:00",
		"link" : "https:\/\/www.joongang.co.kr\/article\/25094893",
		"img_url" : "https:\/\/pds.joongang.co.kr\/news\/component\/htmlphoto_mmdata\/202208\/17\/757052b9-9493-4965-bd03-7da28ac87657.jpg\/_ir_205x115_\/",
		"reg_date" : "2022-08-17T02:19:01.476Z"
	},
	{
		"news_id" : "중앙일보-사회-2022.08.17.10:34",
		"title" : "확인결과 부정투표 없었다…대우조선지회 금속노조 탈퇴 부결",
		"post" : "대우조선해양 하청업체 노조 파업으로 불거진 대우조선 원청 노동조합(금속노조 대우조선지회)의 금속노조 탈퇴안이 부결됐다. 대우조선지회는 조직 형태 변경안 찬반투표 개표 결과 찬성이 2226명(52.7%)에 그쳐 가결 조건인 3분의2를 넘기지 못했다고 17일 밝혔다. 대우조선지회는 지난 7월 21일부터 22일까지 금속노조 탈퇴안을 놓고 조직 형태 변경 여부를 묻는 찬반투표를 진행했다.",
		"source" : "중앙일보",
		"category" : "사회",
		"news_date" : "2022.08.17 10:34",
		"link" : "https:\/\/www.joongang.co.kr\/article\/25094885",
		"img_url" : "https:\/\/pds.joongang.co.kr\/news\/component\/htmlphoto_mmdata\/202208\/17\/8e352975-5af8-4d94-bff5-98b343dc19ad.jpg\/_ir_205x115_\/",
		"reg_date" : "2022-08-17T02:19:01.477Z"
	},
	{
		"news_id" : "중앙일보-사회-2022.08.17.10:00",
		"title" : "[THINK ENGLISH] 홈플러스가 시작한 ‘치킨 전쟁’, 치킨 프랜차이즈들은 반칙이라며 반발",
		"post" : "지난 수요일 서울 합정에 있는 홈플러스 매장에 고객들이 프라이드 치킨을 사기 위해 줄 서 있다. erupt: 분출하다 eatery: 식당 establishment: 기관, 시설 hurl: (거칠게) 던지다, 욕을 퍼붓다, 토하다 accusation: 혐의, 비난, 제소 dumping: 원가보다 저렴하게 물건을 파는 일 프라이드 치킨 전쟁이 다시 시작됐다. overcharge: 바가지를 씌우다 frustrating: 절망적인 rent: 임대 commission: 수수료 delivery worker: 배달 기사 franchise fee: 가맹 수수료 용산에서 프라이드 치킨점을 운영하는 54세의 한 점주는 \"이제 사람들은 홈플러스처럼 싼 가격에 치킨을 파는 게 가능하다고 생각한다.",
		"source" : "중앙일보",
		"category" : "사회",
		"news_date" : "2022.08.17 10:00",
		"link" : "https:\/\/www.joongang.co.kr\/article\/25094878",
		"img_url" : "https:\/\/pds.joongang.co.kr\/news\/component\/htmlphoto_mmdata\/202208\/17\/7bb31b6d-7132-40b9-8cde-55aeffc15809.jpg\/_ir_205x115_\/",
		"reg_date" : "2022-08-17T02:19:01.478Z"
	},
	{
		"news_id" : "중앙일보-사회-2022.08.17.09:39",
		"title" : "6990만원 당당치킨 \"1만원에 선착순\"…당근마켓 황당 판매글",
		"post" : "지난 16일 중고거래 플랫폼 ‘당근마켓’에는 ‘홈플러스 당당치킨 선착순’이라는 제목의 판매 글이 올라왔다. 판매자 A씨는 \"방금 홈플러스에서 12시 타임 줄 서서 샀는데 다른 거 먹을 게 많아서 당당치킨은 안 먹어도 될 것 같다\"며 \"1시5분까지 연락받겠다. \"중고거래 플랫폼이니 무엇을 얼마에 팔든 판매자의 자유\"라며 A씨를 옹호한 의견도 있었지만, 대부분 \"가성비가 좋아서 먹는 건데 웃돈 주고 살 이유가 있나, 황당하다\" \"홈플러스 홈페이지에서 배송 신청하면 오는데 왜 중고거래에서 사냐\" 등의 반응을 보였다.",
		"source" : "중앙일보",
		"category" : "사회",
		"news_date" : "2022.08.17 09:39",
		"link" : "https:\/\/www.joongang.co.kr\/article\/25094875",
		"img_url" : "https:\/\/pds.joongang.co.kr\/news\/component\/htmlphoto_mmdata\/202208\/17\/ef0c9120-abed-4377-afc6-a17823d9ecc9.jpg\/_ir_205x115_\/",
		"reg_date" : "2022-08-17T02:19:01.481Z"
	},
	{
		"news_id" : "중앙일보-사회-2022.08.17.09:31",
		"title" : "[코로나19]신규확진 18만803명, 어제의 2.1배로 급증…넉달 만에 최다",
		"post" : "신종 코로나바이러스 감염증(코로나19) 재유행이 지속되는 가운데 17일 신규 확진자 수는 18만명대로 급증했다. 이날 신규 확진자 수는 전날 발표치(8만4128명)의 2.1배로 급증했다. 지난 11일부터 이날까지 1주일간 신규 확진자 수는 13만7193명→12만8679명→12만4569명→11만9580명→6만2077명→8만4128명→18만803명을 기록했다.",
		"source" : "중앙일보",
		"category" : "사회",
		"news_date" : "2022.08.17 09:31",
		"link" : "https:\/\/www.joongang.co.kr\/article\/25094871",
		"img_url" : "https:\/\/pds.joongang.co.kr\/news\/component\/htmlphoto_mmdata\/202208\/17\/a1edd9c3-6194-4f9b-968f-e78a7c297c3c.jpg\/_ir_205x115_\/",
		"reg_date" : "2022-08-17T02:19:01.482Z"
	},
	{
		"news_id" : "중앙일보-사회-2022.08.17.08:53",
		"title" : "아이 낳아 쓰레기봉투에 유기…'끔찍 범행' 집유 선고 이유는",
		"post" : "자신의 집 화장실에서 낳은 아이를 방치해 숨지게 한 뒤 쓰레기봉투에 담아 유기한 20대 산모에게 집행유예가 선고됐다. A씨는 지난해 5월27일 오전 5시30분쯤 전남 여수의 자택 화장실에서 낳은 아이를 방치해 숨지게 한 혐의로 기소됐다. 다만 \"피고인은 지적 능력이 실생활 연령에 비해 상당히 지연된 전반발달장애 상태인 점, 홀로 분만을 하고 극도의 신체적 탈진과 정신적 흥분상태에서 두려움으로 이 사건 범행에 이르게 된 점, 범죄 전력이 전혀 없는 초범이며 수사기관에서 자신의 범행 사실을 시인한 후 반성하는 점 등을 고려했다\"고 양형 이유를 밝혔다.",
		"source" : "중앙일보",
		"category" : "사회",
		"news_date" : "2022.08.17 08:53",
		"link" : "https:\/\/www.joongang.co.kr\/article\/25094867",
		"img_url" : "https:\/\/pds.joongang.co.kr\/news\/component\/htmlphoto_mmdata\/202208\/17\/92f61011-1ecd-414b-86a2-0132ea042c12.jpg\/_ir_205x115_\/",
		"reg_date" : "2022-08-17T02:19:01.484Z"
	},
	{
		"news_id" : "중앙일보-사회-2022.08.17.08:51",
		"title" : "백지영 호소한 '20억 희귀병약' 첫 투여…환자가 낼 돈은",
		"post" : "1회 투약 비용 약 20억원으로 국내에 도입된 가장 비싼 약인 희귀질환 치료제 '졸겐스마'가 국내에서 처음으로 투여됐다. 17일 제약업계에 따르면 전날 오후 서울대학교병원 채종희 희귀질환센터장(임상유전체의학과·소아청소년과 교수)의 주도로 생후 24개월인 척수성근위축증(SMA) 소아 환자에게 졸겐스마가 투여됐다. 이번에 졸겐스마를 투여받은 소아 환자는 생후 6∼7개월께 척수성근위축증으로 진단받았고, 다른 치료제인 바이오젠의 '스핀라자'를 맞아왔다.",
		"source" : "중앙일보",
		"category" : "사회",
		"news_date" : "2022.08.17 08:51",
		"link" : "https:\/\/www.joongang.co.kr\/article\/25094866",
		"img_url" : "https:\/\/pds.joongang.co.kr\/news\/component\/htmlphoto_mmdata\/202208\/17\/d68172d9-940d-4791-8aa5-8d2d5395dea9.jpg\/_ir_205x115_\/",
		"reg_date" : "2022-08-17T02:19:01.485Z"
	},
	{
		"news_id" : "중앙일보-사회-2022.08.17.08:08",
		"title" : "제주도북부에 호우주의보…제주도산지 등 3곳 호우경보 유지",
		"post" : "기상청은 17일 오전 7시 10분을 기해 제주도 북부에 호우주의보를 발효한다고 밝혔다. 호우주의보는 3시간 강우량이 60㎜ 또는 12시간 강우량이 110㎜ 이상으로 예측될 때 내려진다. 제주도 산지·제주도 남부·제주도 동부에는 호우경보가 내려졌다.",
		"source" : "중앙일보",
		"category" : "사회",
		"news_date" : "2022.08.17 08:08",
		"link" : "https:\/\/www.joongang.co.kr\/article\/25094862",
		"img_url" : "https:\/\/pds.joongang.co.kr\/news\/component\/htmlphoto_mmdata\/202208\/17\/5d769ee3-4baa-42c8-bc40-907f4154da4a.jpg\/_ir_205x115_\/",
		"reg_date" : "2022-08-17T02:19:01.486Z"
	},
	{
		"news_id" : "중앙일보-사회-2022.08.17.06:21",
		"title" : "尹 취임 100일 날…전장연, 보름만에 출근길 지하철 탄다",
		"post" : "지난 1일 집회 후 자제해온 전국장애인차별철폐연대(전장연)가 보름만인 17일 ‘장애인권리예산’ 반영 촉구를 위해 출근길 지하철 집회를 재개한다. 전국장애인차별철폐연대(전장연)는 이날 오전 7시 30분부터 지하철 4호선 삼각지역에서 동대문역사문화공원역, 사당역을 거쳐 삼각지역으로 돌아오는 경로로 시위를 벌인다고 예고했다. 전장연은 \"윤석열 대통령 취임 100일을 맞이하는 날\"이라며 \"취임 100일을 맞아 지구 끝까지 장애인의 권리를 쟁취해 장애인의 완전한 통합과 참여가 보장되는 날까지 출근길에 지하철을 탈 것을 선포하고자 한다\"고 밝혔다.",
		"source" : "중앙일보",
		"category" : "사회",
		"news_date" : "2022.08.17 06:21",
		"link" : "https:\/\/www.joongang.co.kr\/article\/25094856",
		"img_url" : "https:\/\/pds.joongang.co.kr\/news\/component\/htmlphoto_mmdata\/202208\/17\/74d6865d-3189-4e91-8432-91a06c0d187c.jpg\/_ir_205x115_\/",
		"reg_date" : "2022-08-17T02:19:01.487Z"
	},
	{
		"news_id" : "중앙일보-사회-2022.08.17.06:00",
		"title" : "상처주는 말 쉽게 하는 아이, 공감능력 키우려면…이 말투가 답",
		"post" : "공감 능력을 발휘하면 아이는 일방적으로 정보를 전달하는 앵무새가 아닌 상대와 소통하는 말하기를 할 수 있습니다. 서로 말하는 사람과 듣는 사람을 번갈아가며 게임을 하다 보면 상대방의 말에 귀를 기울이고, 이해하기 쉽게 말하는 설명을 익힐 수 있습니다. 설명이 끝나면 말하는 사람이 ‘본 그림’과 듣는 사람이 ‘그린 그림’이 일치하는지 확인하고, 가장 비슷하게 그린 사람이 이기는 게임입니다.",
		"source" : "중앙일보",
		"category" : "사회",
		"news_date" : "2022.08.17 06:00",
		"link" : "https:\/\/www.joongang.co.kr\/article\/25094853",
		"img_url" : "https:\/\/pds.joongang.co.kr\/news\/component\/htmlphoto_mmdata\/202208\/17\/d4d8a4dd-b54d-487e-a61a-814f77eefb0a.jpg\/_ir_205x115_\/",
		"reg_date" : "2022-08-17T02:19:01.488Z"
	},
	{
		"news_id" : "중앙일보-사회-2022.08.17.14:55",
		"title" : "[속보] 한강서 실종된 20대 남성 숨진 채 발견",
		"post" : "",
		"source" : "중앙일보",
		"category" : "사회",
		"news_date" : "2022.08.17 14:55",
		"link" : "https:\/\/www.joongang.co.kr\/article\/25094939",
		"img_url" : "https:\/\/pds.joongang.co.kr\/news\/component\/htmlphoto_mmdata\/202208\/17\/abbb48fc-a58e-45a5-9474-3067b05c600f.jpg\/_ir_205x115_\/",
		"reg_date" : "2022-08-17T05:56:01.417Z"
	}
]}
